odoo8_addon_partner_create_by_vat-8.0.1.0.0.99.dev10-py2.7-nspkg.pth
odoo8_addon_partner_create_by_vat-8.0.1.0.0.99.dev10.dist-info/DESCRIPTION.rst
odoo8_addon_partner_create_by_vat-8.0.1.0.0.99.dev10.dist-info/METADATA
odoo8_addon_partner_create_by_vat-8.0.1.0.0.99.dev10.dist-info/RECORD
odoo8_addon_partner_create_by_vat-8.0.1.0.0.99.dev10.dist-info/WHEEL
odoo8_addon_partner_create_by_vat-8.0.1.0.0.99.dev10.dist-info/metadata.json
odoo8_addon_partner_create_by_vat-8.0.1.0.0.99.dev10.dist-info/namespace_packages.txt
odoo8_addon_partner_create_by_vat-8.0.1.0.0.99.dev10.dist-info/top_level.txt
odoo_addons/partner_create_by_vat/README.rst
odoo_addons/partner_create_by_vat/__init__.py
odoo_addons/partner_create_by_vat/__openerp__.py
odoo_addons/partner_create_by_vat/i18n/de.po
odoo_addons/partner_create_by_vat/i18n/es.po
odoo_addons/partner_create_by_vat/i18n/eu.po
odoo_addons/partner_create_by_vat/i18n/partner_create_by_vat.pot
odoo_addons/partner_create_by_vat/i18n/ro.po
odoo_addons/partner_create_by_vat/i18n/sl.po
odoo_addons/partner_create_by_vat/models/__init__.py
odoo_addons/partner_create_by_vat/models/res_partner.py
odoo_addons/partner_create_by_vat/static/description/customer.png
odoo_addons/partner_create_by_vat/static/description/customer1.png
odoo_addons/partner_create_by_vat/static/description/icon.png
odoo_addons/partner_create_by_vat/tests/__init__.py
odoo_addons/partner_create_by_vat/tests/test_partner_create_by_vat.py
odoo_addons/partner_create_by_vat/views/res_partner_view.xml
