Metadata-Version: 2.0
Name: odoo8-addon-partner-create-by-vat
Version: 8.0.1.0.0.99.dev10
Summary: Using VIES webservice, name and address information will be fetched and added to the partner.
Home-page: https://www.forbiom.eu
Author: Forest and Biomass Services Romania, Odoo Community Association (OCA)
Author-email: support@odoo-community.org
License: AGPL-3
Platform: UNKNOWN
Classifier: Programming Language :: Python
Classifier: Framework :: Odoo
Classifier: License :: OSI Approved :: GNU Affero General Public License v3
Requires-Python: ~=2.7
Requires-Dist: odoo (<9.0a,>=8.0a)
Requires-Dist: python-stdnum
Requires-Dist: suds-jurko
